<?xml version="1.0" encoding="UTF-8"?>
<Word version="1.0" unicode="肢">
  <Stroke>
    <Outline>
      <MoveTo x="376.0" y="1220.0" />
      <QuadTo flexible="false" x1="364.0" y1="1328.0" x2="347.5" y2="1410.5" />
      <QuadTo flexible="false" x1="331.0" y1="1493.0" x2="290.0" y2="1565.5" />
      <QuadTo flexible="false" x1="249.0" y1="1638.0" x2="203.0" y2="1688.0" />
      <QuadTo flexible="false" x1="157.0" y1="1738.0" x2="125.0" y2="1759.0" />
      <LineTo flexible="false" x="95.0" y="1779.0" />
      <QuadTo flexible="false" x1="79.0" y1="1790.0" x2="69.0" y2="1780.0" />
      <QuadTo flexible="false" x1="59.0" y1="1770.0" x2="71.0" y2="1756.0" />
      <LineTo flexible="false" x="99.0" y="1726.0" />
      <QuadTo flexible="false" x1="119.0" y1="1704.0" x2="157.5" y2="1646.5" />
      <QuadTo flexible="false" x1="196.0" y1="1589.0" x2="221.0" y2="1527.0" />
      <QuadTo flexible="false" x1="246.0" y1="1465.0" x2="265.0" y2="1370.5" />
      <QuadTo flexible="false" x1="284.0" y1="1276.0" x2="291.0" y2="1189.0" />
      <QuadTo flexible="false" x1="298.0" y1="1102.0" x2="303.0" y2="937.5" />
      <QuadTo flexible="false" x1="308.0" y1="773.0" x2="309.0" y2="718.5" />
      <QuadTo flexible="false" x1="310.0" y1="664.0" x2="306.0" y2="611.0" />
      <QuadTo flexible="false" x1="303.0" y1="582.0" x2="297.0" y2="548.5" />
      <QuadTo flexible="false" x1="291.0" y1="515.0" x2="278.5" y2="491.0" />
      <QuadTo flexible="false" x1="266.0" y1="467.0" x2="269.0" y2="456.0" />
      <QuadTo flexible="false" x1="272.0" y1="445.0" x2="282.5" y2="440.0" />
      <QuadTo flexible="false" x1="293.0" y1="435.0" x2="315.0" y2="441.0" />
      <QuadTo flexible="false" x1="339.0" y1="448.0" x2="374.0" y2="457.0" />
      <LineTo flexible="false" x="412.0" y="467.0" />
      <QuadTo flexible="true" x1="435.0" y1="473.0" x2="434.0" y2="511.0" />
      <QuadTo flexible="false" x1="429.0" y1="525.0" x2="422.5" y2="548.0" />
      <QuadTo flexible="false" x1="416.0" y1="571.0" x2="415.0" y2="589.0" />
      <LineTo flexible="false" x="403.0" y="691.0" />
      <LineTo flexible="true" x="405.0" y="738.0" />
      <QuadTo flexible="false" x1="402.0" y1="799.0" x2="399.0" y2="865.5" />
      <QuadTo flexible="false" x1="396.0" y1="932.0" x2="390.5" y2="1005.0" />
      <QuadTo flexible="false" x1="385.0" y1="1078.0" x2="383.0" y2="1100.0" />
      <LineTo flexible="false" x="377.0" y="1153.0" />
      <LineTo flexible="true" x="376.0" y="1220.0" />
    </Outline>
    <Track>
      <MoveTo x="354.0" y="460.0" />
      <MoveTo x="353.0" y="946.0" />
      <MoveTo x="290.0" y="1444.0" />
      <MoveTo x="77.0" y="1773.0" size="85.0" />
    </Track>
  </Stroke>
  <Stroke>
    <Outline>
      <MoveTo x="412.0" y="467.0" />
      <LineTo flexible="false" x="509.0" y="444.0" />
      <LineTo flexible="false" x="579.0" y="424.0" />
      <QuadTo flexible="false" x1="614.0" y1="415.0" x2="641.0" y2="400.5" />
      <QuadTo flexible="false" x1="668.0" y1="386.0" x2="671.0" y2="385.0" />
      <QuadTo flexible="false" x1="687.0" y1="384.0" x2="717.0" y2="401.0" />
      <QuadTo flexible="false" x1="747.0" y1="418.0" x2="770.0" y2="436.0" />
      <QuadTo flexible="false" x1="793.0" y1="454.0" x2="806.5" y2="472.0" />
      <QuadTo flexible="false" x1="820.0" y1="490.0" x2="818.0" y2="500.0" />
      <QuadTo flexible="false" x1="817.0" y1="505.0" x2="802.5" y2="523.5" />
      <QuadTo flexible="false" x1="788.0" y1="542.0" x2="783.0" y2="566.0" />
      <QuadTo flexible="false" x1="778.0" y1="590.0" x2="777.0" y2="642.0" />
      <LineTo flexible="false" x="774.0" y="707.0" />
      <QuadTo flexible="false" x1="772.0" y1="743.0" x2="771.0" y2="877.0" />
      <LineTo flexible="false" x="765.0" y="1459.0" />
      <QuadTo flexible="false" x1="763.0" y1="1623.0" x2="755.5" y2="1673.0" />
      <QuadTo flexible="false" x1="748.0" y1="1723.0" x2="725.0" y2="1761.0" />
      <QuadTo flexible="false" x1="702.0" y1="1799.0" x2="672.5" y2="1821.0" />
      <QuadTo flexible="false" x1="643.0" y1="1843.0" x2="626.0" y2="1840.0" />
      <QuadTo flexible="false" x1="612.0" y1="1838.0" x2="592.0" y2="1806.0" />
      <QuadTo flexible="false" x1="572.0" y1="1774.0" x2="521.0" y2="1715.0" />
      <LineTo flexible="false" x="472.0" y="1658.0" />
      <LineTo flexible="false" x="451.0" y="1637.0" />
      <QuadTo flexible="false" x1="440.0" y1="1627.0" x2="447.5" y2="1620.5" />
      <QuadTo flexible="false" x1="455.0" y1="1614.0" x2="470.0" y2="1620.0" />
      <LineTo flexible="false" x="504.0" y="1637.0" />
      <QuadTo flexible="false" x1="554.0" y1="1663.0" x2="577.0" y2="1660.5" />
      <QuadTo flexible="false" x1="600.0" y1="1658.0" x2="617.5" y2="1642.5" />
      <QuadTo flexible="false" x1="635.0" y1="1627.0" x2="639.0" y2="1561.0" />
      <LineTo flexible="false" x="652.0" y="1376.0" />
      <LineTo flexible="false" x="665.0" y="1034.0" />
      <LineTo flexible="true" x="668.0" y="988.0" />
      <LineTo flexible="false" x="668.0" y="886.0" />
      <LineTo flexible="true" x="665.0" y="796.0" />
      <LineTo flexible="false" x="668.0" y="614.0" />
      <QuadTo flexible="false" x1="668.0" y1="569.0" x2="662.5" y2="533.0" />
      <QuadTo flexible="false" x1="657.0" y1="497.0" x2="648.0" y2="489.0" />
      <QuadTo flexible="false" x1="639.0" y1="481.0" x2="606.0" y2="483.5" />
      <QuadTo flexible="false" x1="573.0" y1="486.0" x2="554.0" y2="489.0" />
      <LineTo flexible="false" x="434.0" y="511.0" />
      <LineTo flexible="true" x="412.0" y="467.0" />
    </Outline>
    <Track>
      <MoveTo x="416.0" y="444.0" size="95.0" />
      <MoveTo x="670.0" y="356.0" size="75.0" />
      <MoveTo x="772.0" y="411.0" size="80.0" />
      <MoveTo x="715.0" y="942.0" />
      <MoveTo x="706.0" y="1416.0" />
      <MoveTo x="722.0" y="1816.0" />
      <MoveTo x="463.0" y="1628.0" />
    </Track>
  </Stroke>
  <Stroke>
    <Outline>
      <MoveTo x="668.0" y="886.0" />
      <QuadTo flexible="false" x1="646.0" y1="894.0" x2="628.5" y2="896.5" />
      <QuadTo flexible="false" x1="611.0" y1="899.0" x2="583.5" y2="891.0" />
      <QuadTo flexible="false" x1="556.0" y1="883.0" x2="502.0" y2="834.0" />
      <QuadTo flexible="false" x1="448.0" y1="785.0" x2="443.0" y2="778.0" />
      <LineTo flexible="false" x="405.0" y="738.0" />
      <LineTo flexible="true" x="403.0" y="691.0" />
      <QuadTo flexible="false" x1="446.0" y1="699.0" x2="481.0" y2="706.5" />
      <QuadTo flexible="false" x1="516.0" y1="714.0" x2="564.0" y2="731.5" />
      <QuadTo flexible="false" x1="612.0" y1="749.0" x2="630.0" y2="765.0" />
      <LineTo flexible="false" x="665.0" y="796.0" />
      <LineTo flexible="true" x="668.0" y="886.0" />
    </Outline>
    <Track>
      <MoveTo x="413.0" y="714.0" size="100.0" />
      <MoveTo x="656.0" y="840.0" size="100.0" />
    </Track>
  </Stroke>
  <Stroke>
    <Outline>
      <MoveTo x="665.0" y="1034.0" />
      <LineTo flexible="false" x="574.0" y="1131.0" />
      <LineTo flexible="false" x="538.0" y="1168.0" />
      <QuadTo flexible="false" x1="523.0" y1="1185.0" x2="511.0" y2="1202.5" />
      <QuadTo flexible="false" x1="499.0" y1="1220.0" x2="490.5" y2="1236.5" />
      <QuadTo flexible="false" x1="482.0" y1="1253.0" x2="476.0" y2="1257.0" />
      <QuadTo flexible="false" x1="454.0" y1="1271.0" x2="437.0" y2="1257.0" />
      <LineTo flexible="false" x="376.0" y="1220.0" />
      <LineTo flexible="true" x="377.0" y="1153.0" />
      <QuadTo flexible="false" x1="408.0" y1="1143.0" x2="418.5" y2="1138.5" />
      <QuadTo flexible="false" x1="429.0" y1="1134.0" x2="473.0" y2="1111.0" />
      <QuadTo flexible="false" x1="517.0" y1="1088.0" x2="527.0" y2="1081.0" />
      <LineTo flexible="false" x="668.0" y="988.0" />
      <LineTo flexible="true" x="665.0" y="1034.0" />
    </Outline>
    <Track>
      <MoveTo x="402.0" y="1220.0" size="100.0" />
      <MoveTo x="663.0" y="1010.0" size="95.0" />
    </Track>
  </Stroke>
  <Stroke>
    <Outline>
      <MoveTo x="1286.0" y="655.0" />
      <LineTo flexible="false" x="1470.0" y="617.0" />
      <LineTo flexible="false" x="1547.0" y="596.0" />
      <QuadTo flexible="false" x1="1571.0" y1="590.0" x2="1586.0" y2="590.0" />
      <QuadTo flexible="false" x1="1604.0" y1="591.0" x2="1626.5" y2="602.0" />
      <QuadTo flexible="false" x1="1649.0" y1="613.0" x2="1668.5" y2="625.5" />
      <QuadTo flexible="false" x1="1688.0" y1="638.0" x2="1705.0" y2="655.0" />
      <QuadTo flexible="false" x1="1722.0" y1="672.0" x2="1719.5" y2="682.5" />
      <QuadTo flexible="false" x1="1717.0" y1="693.0" x2="1694.0" y2="700.0" />
      <QuadTo flexible="false" x1="1677.0" y1="706.0" x2="1630.5" y2="705.5" />
      <QuadTo flexible="false" x1="1584.0" y1="705.0" x2="1503.0" y2="712.5" />
      <QuadTo flexible="false" x1="1422.0" y1="720.0" x2="1391.0" y2="724.0" />
      <LineTo flexible="false" x="1291.0" y="738.0" />
      <LineTo flexible="true" x="1169.0" y="765.0" />
      <QuadTo flexible="false" x1="1106.0" y1="774.0" x2="1077.0" y2="782.0" />
      <LineTo flexible="false" x="1016.0" y="800.0" />
      <QuadTo flexible="false" x1="992.0" y1="806.0" x2="971.0" y2="804.0" />
      <QuadTo flexible="false" x1="944.0" y1="803.0" x2="906.5" y2="789.0" />
      <QuadTo flexible="false" x1="869.0" y1="775.0" x2="856.5" y2="761.0" />
      <QuadTo flexible="false" x1="844.0" y1="747.0" x2="845.5" y2="739.5" />
      <QuadTo flexible="false" x1="847.0" y1="732.0" x2="860.0" y2="730.0" />
      <LineTo flexible="false" x="941.0" y="717.0" />
      <LineTo flexible="false" x="1094.0" y="689.0" />
      <LineTo flexible="false" x="1166.0" y="676.0" />
      <LineTo flexible="true" x="1286.0" y="655.0" />
    </Outline>
    <Track>
      <MoveTo x="878.0" y="764.0" />
      <MoveTo x="1271.0" y="696.0" />
      <MoveTo x="1693.0" y="656.0" />
    </Track>
  </Stroke>
  <Stroke>
    <Outline>
      <MoveTo x="1166.0" y="676.0" />
      <LineTo flexible="false" x="1172.0" y="451.0" />
      <QuadTo flexible="false" x1="1172.0" y1="418.0" x2="1170.0" y2="394.0" />
      <QuadTo flexible="false" x1="1168.0" y1="370.0" x2="1162.5" y2="342.5" />
      <QuadTo flexible="false" x1="1157.0" y1="315.0" x2="1152.0" y2="295.5" />
      <QuadTo flexible="false" x1="1147.0" y1="276.0" x2="1134.5" y2="255.0" />
      <QuadTo flexible="false" x1="1122.0" y1="234.0" x2="1121.5" y2="221.5" />
      <QuadTo flexible="false" x1="1121.0" y1="209.0" x2="1131.0" y2="200.0" />
      <QuadTo flexible="false" x1="1141.0" y1="191.0" x2="1167.0" y2="192.0" />
      <QuadTo flexible="false" x1="1194.0" y1="194.0" x2="1219.5" y2="200.0" />
      <QuadTo flexible="false" x1="1245.0" y1="206.0" x2="1266.0" y2="214.0" />
      <QuadTo flexible="false" x1="1287.0" y1="222.0" x2="1306.0" y2="235.0" />
      <QuadTo flexible="false" x1="1325.0" y1="248.0" x2="1328.0" y2="261.0" />
      <QuadTo flexible="false" x1="1331.0" y1="274.0" x2="1317.0" y2="308.0" />
      <QuadTo flexible="false" x1="1308.0" y1="328.0" x2="1302.0" y2="358.5" />
      <QuadTo flexible="false" x1="1296.0" y1="389.0" x2="1294.0" y2="413.5" />
      <QuadTo flexible="false" x1="1292.0" y1="438.0" x2="1291.0" y2="475.0" />
      <LineTo flexible="false" x="1286.0" y="655.0" />
      <LineTo flexible="true" x="1291.0" y="738.0" />
      <LineTo flexible="false" x="1286.0" y="1047.0" />
      <QuadTo flexible="true" x1="1233.0" y1="1116.0" x2="1172.0" y2="1069.0" />
      <LineTo flexible="false" x="1169.0" y="765.0" />
      <LineTo flexible="true" x="1166.0" y="676.0" />
    </Outline>
    <Track>
      <MoveTo x="1220.0" y="203.0" />
      <MoveTo x="1223.0" y="703.0" />
      <MoveTo x="1226.0" y="1076.0" />
    </Track>
  </Stroke>
  <Stroke>
    <Outline>
      <MoveTo x="1286.0" y="1047.0" />
      <QuadTo flexible="false" x1="1338.0" y1="1032.0" x2="1368.0" y2="1021.0" />
      <QuadTo flexible="false" x1="1398.0" y1="1010.0" x2="1424.0" y2="996.0" />
      <QuadTo flexible="false" x1="1450.0" y1="982.0" x2="1461.0" y2="980.0" />
      <QuadTo flexible="false" x1="1480.0" y1="978.0" x2="1504.0" y2="989.5" />
      <QuadTo flexible="false" x1="1528.0" y1="1001.0" x2="1567.0" y2="1020.5" />
      <QuadTo flexible="false" x1="1606.0" y1="1040.0" x2="1621.0" y2="1054.5" />
      <QuadTo flexible="false" x1="1636.0" y1="1069.0" x2="1633.0" y2="1084.0" />
      <QuadTo flexible="false" x1="1631.0" y1="1092.0" x2="1615.0" y2="1108.0" />
      <QuadTo flexible="false" x1="1599.0" y1="1124.0" x2="1584.5" y2="1141.5" />
      <QuadTo flexible="false" x1="1570.0" y1="1159.0" x2="1549.0" y2="1196.0" />
      <QuadTo flexible="false" x1="1528.0" y1="1233.0" x2="1493.0" y2="1301.0" />
      <QuadTo flexible="false" x1="1458.0" y1="1369.0" x2="1455.0" y2="1373.0" />
      <LineTo flexible="false" x="1375.0" y="1499.0" />
      <LineTo flexible="true" x="1294.0" y="1580.0" />
      <QuadTo flexible="false" x1="1228.0" y1="1624.0" x2="1185.5" y2="1648.5" />
      <QuadTo flexible="false" x1="1143.0" y1="1673.0" x2="1081.0" y2="1699.0" />
      <QuadTo flexible="false" x1="1019.0" y1="1725.0" x2="949.5" y2="1746.0" />
      <QuadTo flexible="false" x1="880.0" y1="1767.0" x2="826.0" y2="1771.0" />
      <LineTo flexible="false" x="769.0" y="1776.0" />
      <QuadTo flexible="false" x1="752.0" y1="1778.0" x2="752.5" y2="1766.5" />
      <QuadTo flexible="false" x1="753.0" y1="1755.0" x2="765.0" y2="1750.0" />
      <LineTo flexible="false" x="822.0" y="1730.0" />
      <QuadTo flexible="false" x1="883.0" y1="1709.0" x2="942.0" y2="1683.0" />
      <QuadTo flexible="false" x1="1001.0" y1="1657.0" x2="1069.0" y2="1619.5" />
      <QuadTo flexible="false" x1="1137.0" y1="1582.0" x2="1162.0" y2="1557.0" />
      <LineTo flexible="false" x="1230.0" y="1493.0" />
      <LineTo flexible="true" x="1283.0" y="1428.0" />
      <QuadTo flexible="false" x1="1320.0" y1="1372.0" x2="1335.5" y2="1343.0" />
      <QuadTo flexible="false" x1="1351.0" y1="1314.0" x2="1372.5" y2="1260.5" />
      <QuadTo flexible="false" x1="1394.0" y1="1207.0" x2="1405.0" y2="1180.5" />
      <QuadTo flexible="false" x1="1416.0" y1="1154.0" x2="1413.5" y2="1131.5" />
      <QuadTo flexible="false" x1="1411.0" y1="1109.0" x2="1398.0" y2="1101.0" />
      <QuadTo flexible="false" x1="1385.0" y1="1093.0" x2="1357.5" y2="1100.5" />
      <QuadTo flexible="false" x1="1330.0" y1="1108.0" x2="1280.0" y2="1119.0" />
      <LineTo flexible="false" x="1163.0" y="1147.0" />
      <LineTo flexible="false" x="1050.0" y="1173.0" />
      <LineTo flexible="true" x="966.0" y="1188.0" />
      <LineTo flexible="false" x="913.0" y="1149.0" />
      <QuadTo flexible="false" x1="895.0" y1="1134.0" x2="895.5" y2="1123.5" />
      <QuadTo flexible="false" x1="896.0" y1="1113.0" x2="905.5" y2="1102.5" />
      <QuadTo flexible="false" x1="915.0" y1="1092.0" x2="962.5" y2="1094.5" />
      <QuadTo flexible="false" x1="1010.0" y1="1097.0" x2="1072.0" y2="1086.0" />
      <LineTo flexible="false" x="1172.0" y="1069.0" />
      <LineTo flexible="true" x="1286.0" y="1047.0" />
    </Outline>
    <Track>
      <MoveTo x="918.0" y="1110.0" />
      <MoveTo x="1460.0" y="944.0" size="85.0" />
      <MoveTo x="1574.0" y="990.0" size="90.0" />
      <MoveTo x="1425.0" y="1314.0" />
      <MoveTo x="1179.0" y="1603.0" />
      <MoveTo x="768.0" y="1767.0" size="95.0" />
    </Track>
  </Stroke>
  <Stroke>
    <Outline>
      <MoveTo x="1375.0" y="1499.0" />
      <QuadTo flexible="false" x1="1417.0" y1="1533.0" x2="1464.0" y2="1566.5" />
      <QuadTo flexible="false" x1="1511.0" y1="1600.0" x2="1596.0" y2="1637.5" />
      <QuadTo flexible="false" x1="1681.0" y1="1675.0" x2="1772.0" y2="1704.0" />
      <LineTo flexible="false" x="1878.0" y="1737.0" />
      <QuadTo flexible="false" x1="1919.0" y1="1751.0" x2="1934.0" y2="1754.0" />
      <LineTo flexible="false" x="1965.0" y="1762.0" />
      <QuadTo flexible="false" x1="1985.0" y1="1768.0" x2="1979.5" y2="1783.0" />
      <QuadTo flexible="false" x1="1974.0" y1="1798.0" x2="1956.0" y2="1803.0" />
      <LineTo flexible="false" x="1929.0" y="1811.0" />
      <QuadTo flexible="false" x1="1897.0" y1="1821.0" x2="1854.0" y2="1828.0" />
      <LineTo flexible="false" x="1722.0" y="1848.0" />
      <QuadTo flexible="false" x1="1629.0" y1="1864.0" x2="1594.0" y2="1859.0" />
      <QuadTo flexible="false" x1="1554.0" y1="1855.0" x2="1516.0" y2="1833.0" />
      <QuadTo flexible="false" x1="1478.0" y1="1811.0" x2="1413.0" y2="1732.5" />
      <QuadTo flexible="false" x1="1348.0" y1="1654.0" x2="1338.0" y2="1639.0" />
      <LineTo flexible="false" x="1294.0" y="1580.0" />
      <LineTo flexible="true" x="1230.0" y="1493.0" />
      <QuadTo flexible="false" x1="1215.0" y1="1477.0" x2="1200.5" y2="1460.0" />
      <QuadTo flexible="false" x1="1186.0" y1="1443.0" x2="1140.5" y2="1383.5" />
      <QuadTo flexible="false" x1="1095.0" y1="1324.0" x2="1079.0" y2="1306.0" />
      <QuadTo flexible="false" x1="1063.0" y1="1288.0" x2="1022.5" y2="1244.5" />
      <QuadTo flexible="false" x1="982.0" y1="1201.0" x2="966.0" y2="1188.0" />
      <LineTo flexible="true" x="1050.0" y="1173.0" />
      <QuadTo flexible="false" x1="1083.0" y1="1206.0" x2="1098.0" y2="1222.0" />
      <QuadTo flexible="false" x1="1113.0" y1="1238.0" x2="1172.0" y2="1303.0" />
      <LineTo flexible="false" x="1283.0" y="1428.0" />
      <LineTo flexible="true" x="1375.0" y="1499.0" />
    </Outline>
    <Track>
      <MoveTo x="1020.0" y="1186.0" />
      <MoveTo x="1294.0" y="1491.0" size="100.0" />
      <MoveTo x="1581.0" y="1744.0" size="170.0" />
      <MoveTo x="1968.0" y="1777.0" size="105.0" />
    </Track>
  </Stroke>
</Word>

