<?xml version="1.0" encoding="UTF-8"?>
<Word version="1.0" unicode="辜">
  <Stroke>
    <Outline>
      <MoveTo x="983.0" y="373.0" />
      <LineTo flexible="false" x="849.0" y="385.0" />
      <QuadTo flexible="false" x1="732.0" y1="396.0" x2="711.0" y2="395.5" />
      <QuadTo flexible="false" x1="690.0" y1="395.0" x2="646.5" y2="390.5" />
      <QuadTo flexible="false" x1="603.0" y1="386.0" x2="589.0" y2="368.0" />
      <QuadTo flexible="false" x1="575.0" y1="350.0" x2="581.0" y2="342.5" />
      <QuadTo flexible="false" x1="587.0" y1="335.0" x2="602.0" y2="333.0" />
      <LineTo flexible="false" x="686.0" y="326.0" />
      <QuadTo flexible="false" x1="792.0" y1="318.0" x2="833.0" y2="313.0" />
      <LineTo flexible="false" x="994.0" y="297.0" />
      <LineTo flexible="true" x="1105.0" y="279.0" />
      <QuadTo flexible="false" x1="1193.0" y1="268.0" x2="1239.5" y2="261.0" />
      <QuadTo flexible="false" x1="1286.0" y1="254.0" x2="1329.0" y2="241.0" />
      <QuadTo flexible="false" x1="1372.0" y1="228.0" x2="1386.0" y2="227.0" />
      <QuadTo flexible="false" x1="1404.0" y1="227.0" x2="1432.0" y2="235.0" />
      <QuadTo flexible="false" x1="1460.0" y1="243.0" x2="1484.5" y2="258.0" />
      <QuadTo flexible="false" x1="1509.0" y1="273.0" x2="1508.0" y2="286.0" />
      <QuadTo flexible="false" x1="1506.0" y1="297.0" x2="1496.0" y2="304.0" />
      <QuadTo flexible="false" x1="1486.0" y1="311.0" x2="1446.0" y2="316.0" />
      <LineTo flexible="false" x="1374.0" y="326.0" />
      <LineTo flexible="false" x="1235.0" y="346.0" />
      <LineTo flexible="false" x="1087.0" y="363.0" />
      <LineTo flexible="true" x="983.0" y="373.0" />
    </Outline>
    <Track>
      <MoveTo x="596.0" y="356.0" />
      <MoveTo x="863.0" y="350.0" />
      <MoveTo x="1406.0" y="280.0" />
      <MoveTo x="1486.0" y="280.0" />
    </Track>
  </Stroke>
  <Stroke>
    <Outline>
      <MoveTo x="955.0" y="528.0" />
      <LineTo flexible="false" x="983.0" y="373.0" />
      <LineTo flexible="true" x="994.0" y="297.0" />
      <LineTo flexible="false" x="1001.0" y="240.0" />
      <QuadTo flexible="false" x1="1002.0" y1="225.0" x2="1002.5" y2="194.5" />
      <QuadTo flexible="false" x1="1003.0" y1="164.0" x2="991.5" y2="134.0" />
      <QuadTo flexible="false" x1="980.0" y1="104.0" x2="981.0" y2="94.0" />
      <QuadTo flexible="false" x1="982.0" y1="84.0" x2="991.0" y2="77.0" />
      <QuadTo flexible="false" x1="1000.0" y1="70.0" x2="1030.0" y2="79.0" />
      <QuadTo flexible="false" x1="1055.0" y1="88.0" x2="1092.0" y2="102.0" />
      <QuadTo flexible="false" x1="1129.0" y1="116.0" x2="1145.0" y2="131.0" />
      <QuadTo flexible="false" x1="1161.0" y1="146.0" x2="1161.0" y2="158.0" />
      <QuadTo flexible="false" x1="1160.0" y1="167.0" x2="1143.0" y2="188.5" />
      <QuadTo flexible="false" x1="1126.0" y1="210.0" x2="1124.0" y2="220.0" />
      <LineTo flexible="false" x="1105.0" y="279.0" />
      <LineTo flexible="true" x="1087.0" y="363.0" />
      <LineTo flexible="false" x="1040.0" y="516.0" />
      <QuadTo flexible="true" x1="962.5" y1="597.0" x2="955.0" y2="528.0" />
    </Outline>
    <Track>
      <MoveTo x="1060.0" y="106.0" />
      <MoveTo x="1023.0" y="426.0" />
      <MoveTo x="1013.0" y="506.0" />
    </Track>
  </Stroke>
  <Stroke>
    <Outline>
      <MoveTo x="820.0" y="803.0" />
      <QuadTo flexible="false" x1="814.0" y1="814.0" x2="806.5" y2="822.0" />
      <QuadTo flexible="false" x1="799.0" y1="830.0" x2="788.5" y2="830.5" />
      <QuadTo flexible="false" x1="778.0" y1="831.0" x2="770.0" y2="820.0" />
      <QuadTo flexible="false" x1="762.0" y1="809.0" x2="754.0" y2="786.0" />
      <LineTo flexible="false" x="709.0" y="665.0" />
      <QuadTo flexible="false" x1="689.0" y1="612.0" x2="674.0" y2="592.5" />
      <QuadTo flexible="false" x1="659.0" y1="573.0" x2="658.5" y2="563.5" />
      <QuadTo flexible="false" x1="658.0" y1="554.0" x2="667.0" y2="546.0" />
      <QuadTo flexible="false" x1="668.0" y1="546.0" x2="709.0" y2="546.0" />
      <LineTo flexible="false" x="763.0" y="551.0" />
      <LineTo flexible="true" x="798.0" y="596.0" />
      <LineTo flexible="false" x="817.0" y="741.0" />
      <LineTo flexible="true" x="820.0" y="803.0" />
    </Outline>
    <Track>
      <MoveTo x="703.0" y="556.0" />
      <MoveTo x="773.0" y="650.0" />
      <MoveTo x="796.0" y="810.0" />
    </Track>
  </Stroke>
  <Stroke>
    <Outline>
      <MoveTo x="763.0" y="551.0" />
      <LineTo flexible="false" x="955.0" y="528.0" />
      <LineTo flexible="true" x="1040.0" y="516.0" />
      <LineTo flexible="false" x="1178.0" y="489.0" />
      <QuadTo flexible="false" x1="1245.0" y1="476.0" x2="1268.0" y2="468.0" />
      <QuadTo flexible="false" x1="1291.0" y1="460.0" x2="1300.0" y2="460.0" />
      <QuadTo flexible="false" x1="1313.0" y1="461.0" x2="1337.5" y2="473.0" />
      <QuadTo flexible="false" x1="1362.0" y1="485.0" x2="1378.5" y2="495.5" />
      <QuadTo flexible="false" x1="1395.0" y1="506.0" x2="1413.0" y2="525.0" />
      <QuadTo flexible="false" x1="1431.0" y1="544.0" x2="1427.0" y2="557.0" />
      <QuadTo flexible="false" x1="1425.0" y1="563.0" x2="1410.0" y2="577.0" />
      <QuadTo flexible="false" x1="1395.0" y1="591.0" x2="1384.0" y2="613.0" />
      <LineTo flexible="false" x="1334.0" y="707.0" />
      <QuadTo flexible="true" x1="1241.0" y1="768.0" x2="1248.0" y2="689.0" />
      <LineTo flexible="false" x="1268.0" y="605.0" />
      <QuadTo flexible="false" x1="1277.0" y1="565.0" x2="1267.5" y2="554.0" />
      <QuadTo flexible="false" x1="1258.0" y1="543.0" x2="1226.0" y2="546.0" />
      <LineTo flexible="false" x="798.0" y="596.0" />
      <QuadTo flexible="true" x1="690.5" y1="583.5" x2="763.0" y2="551.0" />
    </Outline>
    <Track>
      <MoveTo x="800.0" y="580.0" />
      <MoveTo x="1240.0" y="513.0" />
      <MoveTo x="1400.0" y="540.0" />
      <MoveTo x="1333.0" y="600.0" />
      <MoveTo x="1293.0" y="693.0" />
    </Track>
  </Stroke>
  <Stroke>
    <Outline>
      <MoveTo x="964.0" y="787.0" />
      <LineTo flexible="false" x="820.0" y="803.0" />
      <QuadTo flexible="true" x1="723.5" y1="772.0" x2="817.0" y2="741.0" />
      <LineTo flexible="false" x="1248.0" y="689.0" />
      <QuadTo flexible="true" x1="1311.0" y1="678.0" x2="1334.0" y2="707.0" />
      <QuadTo flexible="false" x1="1342.0" y1="715.0" x2="1350.0" y2="723.5" />
      <QuadTo flexible="false" x1="1358.0" y1="732.0" x2="1356.5" y2="739.5" />
      <QuadTo flexible="false" x1="1355.0" y1="747.0" x2="1348.0" y2="751.5" />
      <QuadTo flexible="false" x1="1341.0" y1="756.0" x2="1286.0" y2="761.0" />
      <LineTo flexible="false" x="1016.0" y="789.0" />
      <LineTo flexible="true" x="964.0" y="787.0" />
    </Outline>
    <Track>
      <MoveTo x="830.0" y="776.0" />
      <MoveTo x="1270.0" y="730.0" />
      <MoveTo x="1340.0" y="730.0" />
    </Track>
  </Stroke>
  <Stroke>
    <Outline>
      <MoveTo x="1023.0" y="914.0" />
      <QuadTo flexible="false" x1="1014.0" y1="895.0" x2="1009.5" y2="885.0" />
      <QuadTo flexible="false" x1="1005.0" y1="875.0" x2="995.0" y2="847.5" />
      <QuadTo flexible="false" x1="985.0" y1="820.0" x2="981.0" y2="813.0" />
      <LineTo flexible="false" x="964.0" y="787.0" />
      <QuadTo flexible="true" x1="915.0" y1="748.0" x2="1016.0" y2="789.0" />
      <QuadTo flexible="false" x1="1047.0" y1="798.0" x2="1062.5" y2="806.0" />
      <QuadTo flexible="false" x1="1078.0" y1="814.0" x2="1091.0" y2="831.0" />
      <QuadTo flexible="false" x1="1104.0" y1="848.0" x2="1100.0" y2="868.0" />
      <LineTo flexible="false" x="1095.0" y="903.0" />
      <QuadTo flexible="true" x1="1059.0" y1="958.5" x2="1023.0" y2="914.0" />
    </Outline>
    <Track>
      <MoveTo x="1010.0" y="796.0" />
      <MoveTo x="1070.0" y="900.0" />
    </Track>
  </Stroke>
  <Stroke>
    <Outline>
      <MoveTo x="793.0" y="1008.0" />
      <QuadTo flexible="false" x1="771.0" y1="1010.0" x2="752.5" y2="1012.5" />
      <QuadTo flexible="false" x1="734.0" y1="1015.0" x2="704.0" y2="1024.0" />
      <QuadTo flexible="false" x1="674.0" y1="1033.0" x2="662.0" y2="1031.0" />
      <QuadTo flexible="false" x1="650.0" y1="1030.0" x2="628.0" y2="1018.0" />
      <QuadTo flexible="false" x1="606.0" y1="1006.0" x2="597.0" y2="999.0" />
      <QuadTo flexible="false" x1="588.0" y1="992.0" x2="578.0" y2="981.5" />
      <QuadTo flexible="false" x1="568.0" y1="971.0" x2="570.0" y2="966.0" />
      <QuadTo flexible="false" x1="572.0" y1="961.0" x2="581.0" y2="959.0" />
      <LineTo flexible="false" x="620.0" y="954.0" />
      <LineTo flexible="false" x="771.0" y="939.0" />
      <LineTo flexible="false" x="1023.0" y="914.0" />
      <LineTo flexible="true" x="1095.0" y="903.0" />
      <LineTo flexible="false" x="1268.0" y="882.0" />
      <QuadTo flexible="false" x1="1322.0" y1="876.0" x2="1350.0" y2="869.0" />
      <QuadTo flexible="false" x1="1378.0" y1="862.0" x2="1389.0" y2="862.0" />
      <QuadTo flexible="false" x1="1406.0" y1="863.0" x2="1429.5" y2="872.5" />
      <QuadTo flexible="false" x1="1453.0" y1="882.0" x2="1471.5" y2="894.0" />
      <QuadTo flexible="false" x1="1490.0" y1="906.0" x2="1504.0" y2="920.5" />
      <QuadTo flexible="false" x1="1518.0" y1="935.0" x2="1515.0" y2="943.0" />
      <QuadTo flexible="false" x1="1512.0" y1="951.0" x2="1505.0" y2="954.5" />
      <QuadTo flexible="false" x1="1498.0" y1="958.0" x2="1448.0" y2="959.0" />
      <LineTo flexible="false" x="1281.0" y="965.0" />
      <LineTo flexible="true" x="1176.0" y="969.0" />
      <LineTo flexible="false" x="830.0" y="1004.0" />
      <LineTo flexible="true" x="793.0" y="1008.0" />
    </Outline>
    <Track>
      <MoveTo x="580.0" y="970.0" />
      <MoveTo x="813.0" y="963.0" />
      <MoveTo x="1240.0" y="920.0" />
      <MoveTo x="1496.0" y="930.0" />
    </Track>
  </Stroke>
  <Stroke>
    <Outline>
      <MoveTo x="858.0" y="1224.0" />
      <QuadTo flexible="false" x1="844.0" y1="1174.0" x2="832.5" y2="1131.0" />
      <QuadTo flexible="false" x1="821.0" y1="1088.0" x2="813.0" y2="1065.0" />
      <LineTo flexible="false" x="793.0" y="1008.0" />
      <QuadTo flexible="true" x1="771.5" y1="961.0" x2="830.0" y2="1004.0" />
      <QuadTo flexible="false" x1="880.0" y1="1047.0" x2="900.5" y2="1073.5" />
      <QuadTo flexible="false" x1="921.0" y1="1100.0" x2="926.0" y2="1122.0" />
      <QuadTo flexible="false" x1="931.0" y1="1150.0" x2="921.0" y2="1181.0" />
      <LineTo flexible="false" x="908.0" y="1223.0" />
      <QuadTo flexible="true" x1="873.0" y1="1278.5" x2="858.0" y2="1224.0" />
    </Outline>
    <Track>
      <MoveTo x="830.0" y="1010.0" />
      <MoveTo x="893.0" y="1170.0" />
      <MoveTo x="890.0" y="1213.0" />
    </Track>
  </Stroke>
  <Stroke>
    <Outline>
      <MoveTo x="1281.0" y="965.0" />
      <QuadTo flexible="false" x1="1301.0" y1="981.0" x2="1315.0" y2="995.0" />
      <QuadTo flexible="false" x1="1329.0" y1="1009.0" x2="1327.0" y2="1021.0" />
      <QuadTo flexible="false" x1="1325.0" y1="1029.0" x2="1318.0" y2="1036.0" />
      <LineTo flexible="false" x="1290.0" y="1058.0" />
      <QuadTo flexible="false" x1="1284.0" y1="1064.0" x2="1273.0" y2="1082.0" />
      <LineTo flexible="false" x="1201.0" y="1197.0" />
      <QuadTo flexible="true" x1="1106.0" y1="1258.0" x2="1151.0" y2="1199.0" />
      <QuadTo flexible="false" x1="1163.0" y1="1153.0" x2="1169.0" y2="1126.0" />
      <QuadTo flexible="false" x1="1175.0" y1="1099.0" x2="1180.5" y2="1060.0" />
      <QuadTo flexible="false" x1="1186.0" y1="1021.0" x2="1184.0" y2="1011.0" />
      <LineTo flexible="false" x="1176.0" y="969.0" />
      <QuadTo flexible="true" x1="1168.5" y1="902.0" x2="1281.0" y2="965.0" />
    </Outline>
    <Track>
      <MoveTo x="1260.0" y="973.0" />
      <MoveTo x="1193.0" y="1126.0" />
      <MoveTo x="1193.0" y="1183.0" />
    </Track>
  </Stroke>
  <Stroke>
    <Outline>
      <MoveTo x="1201.0" y="1197.0" />
      <LineTo flexible="false" x="1481.0" y="1169.0" />
      <QuadTo flexible="false" x1="1559.0" y1="1162.0" x2="1604.5" y2="1154.5" />
      <QuadTo flexible="false" x1="1650.0" y1="1147.0" x2="1662.0" y2="1147.0" />
      <QuadTo flexible="false" x1="1689.0" y1="1148.0" x2="1710.0" y2="1157.5" />
      <QuadTo flexible="false" x1="1731.0" y1="1167.0" x2="1763.0" y2="1185.5" />
      <QuadTo flexible="false" x1="1795.0" y1="1204.0" x2="1806.5" y2="1218.0" />
      <QuadTo flexible="false" x1="1818.0" y1="1232.0" x2="1816.5" y2="1241.5" />
      <QuadTo flexible="false" x1="1815.0" y1="1251.0" x2="1787.0" y2="1258.0" />
      <LineTo flexible="false" x="1645.0" y="1263.0" />
      <LineTo flexible="false" x="1085.0" y="1288.0" />
      <LineTo flexible="true" x="964.0" y="1297.0" />
      <QuadTo flexible="false" x1="884.0" y1="1303.0" x2="816.0" y2="1308.0" />
      <QuadTo flexible="false" x1="748.0" y1="1313.0" x2="644.5" y2="1324.0" />
      <QuadTo flexible="false" x1="541.0" y1="1335.0" x2="490.5" y2="1339.0" />
      <QuadTo flexible="false" x1="440.0" y1="1343.0" x2="400.0" y2="1353.0" />
      <QuadTo flexible="false" x1="360.0" y1="1363.0" x2="350.0" y2="1362.0" />
      <QuadTo flexible="false" x1="330.0" y1="1362.0" x2="302.5" y2="1349.0" />
      <QuadTo flexible="false" x1="275.0" y1="1336.0" x2="261.5" y2="1325.5" />
      <QuadTo flexible="false" x1="248.0" y1="1315.0" x2="238.5" y2="1302.0" />
      <QuadTo flexible="false" x1="229.0" y1="1289.0" x2="231.0" y2="1281.0" />
      <QuadTo flexible="false" x1="233.0" y1="1273.0" x2="246.0" y2="1273.0" />
      <LineTo flexible="false" x="291.0" y="1273.0" />
      <LineTo flexible="false" x="858.0" y="1224.0" />
      <LineTo flexible="true" x="908.0" y="1223.0" />
      <LineTo flexible="false" x="1151.0" y="1199.0" />
      <LineTo flexible="true" x="1201.0" y="1197.0" />
    </Outline>
    <Track>
      <MoveTo x="236.0" y="1286.0" />
      <MoveTo x="503.0" y="1293.0" />
      <MoveTo x="966.0" y="1260.0" />
      <MoveTo x="1426.0" y="1223.0" />
      <MoveTo x="1736.0" y="1213.0" />
      <MoveTo x="1800.0" y="1233.0" />
    </Track>
  </Stroke>
  <Stroke>
    <Outline>
      <MoveTo x="1087.0" y="1451.0" />
      <LineTo flexible="false" x="1295.0" y="1431.0" />
      <QuadTo flexible="false" x1="1351.0" y1="1426.0" x2="1391.0" y2="1415.5" />
      <QuadTo flexible="false" x1="1431.0" y1="1405.0" x2="1443.0" y2="1404.0" />
      <QuadTo flexible="false" x1="1462.0" y1="1404.0" x2="1492.0" y2="1417.0" />
      <QuadTo flexible="false" x1="1522.0" y1="1430.0" x2="1541.0" y2="1440.5" />
      <QuadTo flexible="false" x1="1560.0" y1="1451.0" x2="1578.0" y2="1463.5" />
      <QuadTo flexible="false" x1="1596.0" y1="1476.0" x2="1605.5" y2="1488.5" />
      <QuadTo flexible="false" x1="1615.0" y1="1501.0" x2="1613.0" y2="1508.0" />
      <QuadTo flexible="false" x1="1611.0" y1="1515.0" x2="1601.0" y2="1520.5" />
      <QuadTo flexible="false" x1="1591.0" y1="1526.0" x2="1558.0" y2="1525.0" />
      <LineTo flexible="false" x="1478.0" y="1523.0" />
      <LineTo flexible="false" x="1375.0" y="1518.0" />
      <QuadTo flexible="false" x1="1258.0" y1="1513.0" x2="1186.0" y2="1518.0" />
      <LineTo flexible="false" x="1082.0" y="1525.0" />
      <LineTo flexible="true" x="981.0" y="1533.0" />
      <QuadTo flexible="false" x1="925.0" y1="1539.0" x2="873.5" y2="1545.0" />
      <QuadTo flexible="false" x1="822.0" y1="1551.0" x2="763.0" y2="1561.0" />
      <QuadTo flexible="false" x1="704.0" y1="1571.0" x2="661.5" y2="1583.0" />
      <QuadTo flexible="false" x1="619.0" y1="1595.0" x2="602.0" y2="1594.0" />
      <QuadTo flexible="false" x1="583.0" y1="1594.0" x2="551.5" y2="1582.0" />
      <QuadTo flexible="false" x1="520.0" y1="1570.0" x2="497.5" y2="1556.5" />
      <QuadTo flexible="false" x1="475.0" y1="1543.0" x2="464.5" y2="1529.5" />
      <QuadTo flexible="false" x1="454.0" y1="1516.0" x2="457.5" y2="1506.5" />
      <QuadTo flexible="false" x1="461.0" y1="1497.0" x2="478.0" y2="1497.0" />
      <LineTo flexible="false" x="516.0" y="1498.0" />
      <QuadTo flexible="false" x1="555.0" y1="1500.0" x2="614.5" y2="1496.5" />
      <QuadTo flexible="false" x1="674.0" y1="1493.0" x2="751.0" y2="1483.0" />
      <LineTo flexible="false" x="870.0" y="1468.0" />
      <LineTo flexible="false" x="983.0" y="1456.0" />
      <LineTo flexible="true" x="1087.0" y="1451.0" />
    </Outline>
    <Track>
      <MoveTo x="476.0" y="1523.0" />
      <MoveTo x="740.0" y="1520.0" />
      <MoveTo x="1260.0" y="1470.0" />
      <MoveTo x="1583.0" y="1486.0" />
    </Track>
  </Stroke>
  <Stroke>
    <Outline>
      <MoveTo x="1085.0" y="1288.0" />
      <QuadTo flexible="false" x1="1100.0" y1="1299.0" x2="1112.0" y2="1305.5" />
      <QuadTo flexible="false" x1="1124.0" y1="1312.0" x2="1126.5" y2="1318.5" />
      <QuadTo flexible="false" x1="1129.0" y1="1325.0" x2="1124.0" y2="1337.0" />
      <LineTo flexible="false" x="1107.0" y="1362.0" />
      <QuadTo flexible="false" x1="1094.0" y1="1381.0" x2="1092.0" y2="1404.0" />
      <LineTo flexible="false" x="1087.0" y="1451.0" />
      <LineTo flexible="true" x="1082.0" y="1525.0" />
      <LineTo flexible="false" x="1076.0" y="1730.0" />
      <QuadTo flexible="false" x1="1074.0" y1="1773.0" x2="1067.0" y2="1820.5" />
      <QuadTo flexible="false" x1="1060.0" y1="1868.0" x2="1054.5" y2="1889.0" />
      <QuadTo flexible="false" x1="1049.0" y1="1910.0" x2="1041.0" y2="1932.5" />
      <QuadTo flexible="false" x1="1033.0" y1="1955.0" x2="1025.5" y2="1963.5" />
      <QuadTo flexible="false" x1="1018.0" y1="1972.0" x2="1009.0" y2="1972.5" />
      <QuadTo flexible="false" x1="1000.0" y1="1973.0" x2="991.0" y2="1942.0" />
      <QuadTo flexible="false" x1="985.0" y1="1925.0" x2="982.0" y2="1905.5" />
      <QuadTo flexible="false" x1="979.0" y1="1886.0" x2="980.0" y2="1850.0" />
      <LineTo flexible="false" x="981.0" y="1533.0" />
      <LineTo flexible="true" x="983.0" y="1456.0" />
      <LineTo flexible="false" x="983.0" y="1394.0" />
      <QuadTo flexible="false" x1="983.0" y1="1379.0" x2="973.0" y2="1335.0" />
      <LineTo flexible="false" x="964.0" y="1297.0" />
      <QuadTo flexible="true" x1="964.5" y1="1192.5" x2="1085.0" y2="1288.0" />
    </Outline>
    <Track>
      <MoveTo x="1043.0" y="1293.0" />
      <MoveTo x="1030.0" y="1720.0" />
      <MoveTo x="1016.0" y="1953.0" />
    </Track>
  </Stroke>
</Word>

